<?xml version="1.0" encoding="utf-8" standalone="yes"?><Gesture Name="l~07" Subject="294" Speed="Medium" Number="7" NumPts="128" Milliseconds="328" AppName="GestureCollection" AppVer="0.0" Date="Wednesday, April 13, 2022" TimeOfDay="2:24:48 PM"><Stroke index="1"><Point X="637" Y="221" T="1649873869342" Pressure="128" /><Point X="630" Y="238" T="1649873869344" Pressure="128" /><Point X="629" Y="243" T="1649873869345" Pressure="128" /><Point X="627" Y="249" T="1649873869353" Pressure="128" /><Point X="625" Y="254" T="1649873869362" Pressure="128" /><Point X="623" Y="259" T="1649873869371" Pressure="128" /><Point X="621" Y="264" T="1649873869379" Pressure="128" /><Point X="619" Y="270" T="1649873869389" Pressure="128" /><Point X="615" Y="276" T="1649873869403" Pressure="128" /><Point X="612" Y="281" T="1649873869406" Pressure="128" /><Point X="608" Y="286" T="1649873869418" Pressure="128" /><Point X="604" Y="289" T="1649873869424" Pressure="128" /><Point X="600" Y="292" T="1649873869433" Pressure="128" /><Point X="598" Y="295" T="1649873869441" Pressure="128" /><Point X="595" Y="297" T="1649873869450" Pressure="128" /><Point X="593" Y="299" T="1649873869458" Pressure="128" /><Point X="592" Y="301" T="1649873869467" Pressure="128" /><Point X="590" Y="302" T="1649873869476" Pressure="128" /><Point X="589" Y="303" T="1649873869484" Pressure="128" /><Point X="588" Y="304" T="1649873869493" Pressure="128" /><Point X="587" Y="305" T="1649873869502" Pressure="128" /><Point X="587" Y="306" T="1649873869511" Pressure="128" /><Point X="586" Y="306" T="1649873869520" Pressure="128" /><Point X="586" Y="307" T="1649873869528" Pressure="128" /><Point X="587" Y="307" T="1649873869537" Pressure="128" /><Point X="589" Y="307" T="1649873869545" Pressure="128" /><Point X="594" Y="307" T="1649873869554" Pressure="128" /><Point X="601" Y="307" T="1649873869562" Pressure="128" /><Point X="610" Y="307" T="1649873869572" Pressure="128" /><Point X="621" Y="307" T="1649873869582" Pressure="128" /><Point X="632" Y="307" T="1649873869591" Pressure="128" /><Point X="643" Y="307" T="1649873869600" Pressure="128" /><Point X="656" Y="307" T="1649873869608" Pressure="128" /><Point X="669" Y="306" T="1649873869617" Pressure="128" /><Point X="683" Y="306" T="1649873869643" Pressure="128" /><Point X="695" Y="306" T="1649873869686" Pressure="128" /><Point X="708" Y="305" T="1649873869696" Pressure="128" /><Point X="718" Y="304" T="1649873870584" Pressure="128" /><Point X="728" Y="304" T="1649873870586" Pressure="128" /><Point X="736" Y="303" T="1649873870591" Pressure="128" /><Point X="742" Y="303" T="1649873870600" Pressure="128" /><Point X="746" Y="303" T="1649873870610" Pressure="128" /><Point X="749" Y="302" T="1649873870618" Pressure="128" /><Point X="750" Y="302" T="1649873870627" Pressure="128" /><Point X="751" Y="302" T="1649873870636" Pressure="128" /><Point X="752" Y="302" T="1649873870644" Pressure="128" /><Point X="753" Y="302" T="1649873870653" Pressure="128" /><Point X="753" Y="303" T="1649873870661" Pressure="128" /><Point X="753" Y="303" T="1649873870671" Pressure="128" /></Stroke><Stroke index="2"><Point X="756" Y="279" T="1649873870689" Pressure="128" /><Point X="756" Y="283" T="1649873870698" Pressure="128" /><Point X="756" Y="287" T="1649873870708" Pressure="128" /><Point X="756" Y="293" T="1649873870716" Pressure="128" /><Point X="756" Y="299" T="1649873870725" Pressure="128" /><Point X="756" Y="305" T="1649873870734" Pressure="128" /><Point X="756" Y="311" T="1649873870744" Pressure="128" /><Point X="755" Y="318" T="1649873870752" Pressure="128" /><Point X="755" Y="326" T="1649873870770" Pressure="128" /><Point X="755" Y="333" T="1649873870788" Pressure="128" /><Point X="754" Y="339" T="1649873870842" Pressure="128" /><Point X="753" Y="346" T="1649873870896" Pressure="128" /><Point X="752" Y="355" T="1649873870963" Pressure="128" /><Point X="750" Y="362" T="1649873870972" Pressure="128" /><Point X="748" Y="368" T="1649873870981" Pressure="128" /><Point X="746" Y="374" T="1649873870991" Pressure="128" /><Point X="742" Y="383" T="1649873871000" Pressure="128" /><Point X="739" Y="390" T="1649873871009" Pressure="128" /><Point X="734" Y="398" T="1649873871018" Pressure="128" /><Point X="730" Y="406" T="1649873871026" Pressure="128" /><Point X="724" Y="414" T="1649873871035" Pressure="128" /><Point X="718" Y="421" T="1649873871045" Pressure="128" /><Point X="710" Y="428" T="1649873871055" Pressure="128" /><Point X="702" Y="436" T="1649873871066" Pressure="128" /><Point X="692" Y="443" T="1649873871074" Pressure="128" /><Point X="683" Y="448" T="1649873871083" Pressure="128" /><Point X="674" Y="453" T="1649873871091" Pressure="128" /><Point X="664" Y="457" T="1649873871101" Pressure="128" /><Point X="657" Y="460" T="1649873871109" Pressure="128" /><Point X="650" Y="462" T="1649873871118" Pressure="128" /><Point X="644" Y="463" T="1649873871126" Pressure="128" /><Point X="639" Y="465" T="1649873871136" Pressure="128" /><Point X="636" Y="465" T="1649873871145" Pressure="128" /><Point X="635" Y="466" T="1649873871154" Pressure="128" /><Point X="634" Y="466" T="1649873871168" Pressure="128" /><Point X="633" Y="466" T="1649873871173" Pressure="128" /><Point X="633" Y="467" T="1649873871183" Pressure="128" /><Point X="632" Y="467" T="1649873871191" Pressure="128" /><Point X="633" Y="467" T="1649873871201" Pressure="128" /><Point X="633" Y="467" T="1649873871211" Pressure="128" /></Stroke><Stroke index="3"><Point X="678" Y="290" T="1649873871228" Pressure="128" /><Point X="677" Y="297" T="1649873871238" Pressure="128" /><Point X="676" Y="304" T="1649873871249" Pressure="128" /><Point X="673" Y="311" T="1649873871257" Pressure="128" /><Point X="670" Y="318" T="1649873871269" Pressure="128" /><Point X="667" Y="325" T="1649873871276" Pressure="128" /><Point X="663" Y="333" T="1649873871285" Pressure="128" /><Point X="659" Y="338" T="1649873871293" Pressure="128" /><Point X="656" Y="343" T="1649873871303" Pressure="128" /><Point X="653" Y="347" T="1649873871312" Pressure="128" /><Point X="651" Y="351" T="1649873871322" Pressure="128" /><Point X="648" Y="356" T="1649873871331" Pressure="128" /><Point X="645" Y="360" T="1649873871341" Pressure="128" /><Point X="642" Y="364" T="1649873871351" Pressure="128" /><Point X="639" Y="367" T="1649873871359" Pressure="128" /><Point X="635" Y="369" T="1649873871369" Pressure="128" /><Point X="632" Y="372" T="1649873871377" Pressure="128" /><Point X="630" Y="375" T="1649873871387" Pressure="128" /><Point X="627" Y="378" T="1649873871395" Pressure="128" /><Point X="624" Y="381" T="1649873871405" Pressure="128" /><Point X="621" Y="384" T="1649873871414" Pressure="128" /><Point X="619" Y="388" T="1649873871432" Pressure="128" /><Point X="615" Y="391" T="1649873871478" Pressure="128" /><Point X="612" Y="394" T="1649873871514" Pressure="128" /><Point X="608" Y="397" T="1649873871525" Pressure="128" /><Point X="605" Y="400" T="1649873877466" Pressure="128" /><Point X="602" Y="402" T="1649873877468" Pressure="128" /><Point X="599" Y="405" T="1649873877470" Pressure="128" /><Point X="596" Y="408" T="1649873877478" Pressure="128" /><Point X="593" Y="410" T="1649873877488" Pressure="128" /><Point X="589" Y="413" T="1649873877497" Pressure="128" /><Point X="586" Y="416" T="1649873877505" Pressure="128" /><Point X="583" Y="418" T="1649873877514" Pressure="128" /><Point X="580" Y="420" T="1649873877522" Pressure="128" /><Point X="577" Y="421" T="1649873877531" Pressure="128" /><Point X="575" Y="422" T="1649873877540" Pressure="128" /><Point X="575" Y="422" T="1649873877548" Pressure="128" /></Stroke></Gesture>