<?xml version="1.0" encoding="UTF-8" standalone="yes"?>
<Gesture AppName="PointClouds" AppVer="0.0.0.0" Date="Saturday, April 09, 2022" Millseconds="558" Name="eng~06" NumPts="47" Number="6" Speed="MEDIUM" Subject="1" TimeOfDay="10:01:03 PM">
    <Stroke index="1">
        <Point T="1649559661781" X="221" Y="284"/>
        <Point T="1649559661843" X="221" Y="285"/>
        <Point T="1649559661851" X="221" Y="286"/>
        <Point T="1649559661859" X="221" Y="288"/>
        <Point T="1649559661867" X="221" Y="290"/>
        <Point T="1649559661875" X="220" Y="293"/>
        <Point T="1649559661884" X="219" Y="298"/>
        <Point T="1649559661891" X="217" Y="303"/>
        <Point T="1649559661899" X="214" Y="311"/>
        <Point T="1649559661907" X="210" Y="320"/>
        <Point T="1649559661915" X="206" Y="329"/>
        <Point T="1649559661924" X="201" Y="339"/>
        <Point T="1649559661932" X="196" Y="349"/>
        <Point T="1649559661939" X="193" Y="359"/>
        <Point T="1649559661949" X="190" Y="369"/>
        <Point T="1649559661955" X="187" Y="378"/>
        <Point T="1649559661965" X="185" Y="387"/>
        <Point T="1649559661971" X="183" Y="395"/>
        <Point T="1649559661981" X="180" Y="403"/>
        <Point T="1649559661987" X="177" Y="410"/>
        <Point T="1649559661997" X="175" Y="416"/>
        <Point T="1649559662004" X="173" Y="421"/>
        <Point T="1649559662013" X="172" Y="424"/>
        <Point T="1649559662019" X="171" Y="426"/>
        <Point T="1649559662029" X="171" Y="427"/>
        <Point T="1649559662035" X="170" Y="428"/>
        <Point T="1649559662123" X="171" Y="428"/>
        <Point T="1649559662132" X="172" Y="429"/>
        <Point T="1649559662139" X="174" Y="429"/>
        <Point T="1649559662149" X="177" Y="429"/>
        <Point T="1649559662155" X="182" Y="429"/>
        <Point T="1649559662165" X="188" Y="429"/>
        <Point T="1649559662172" X="196" Y="429"/>
        <Point T="1649559662181" X="205" Y="429"/>
        <Point T="1649559662187" X="214" Y="429"/>
        <Point T="1649559662197" X="223" Y="429"/>
        <Point T="1649559662204" X="233" Y="429"/>
        <Point T="1649559662212" X="245" Y="429"/>
        <Point T="1649559662219" X="256" Y="429"/>
        <Point T="1649559662229" X="265" Y="429"/>
        <Point T="1649559662235" X="273" Y="429"/>
        <Point T="1649559662244" X="278" Y="429"/>
        <Point T="1649559662251" X="281" Y="429"/>
        <Point T="1649559662259" X="283" Y="429"/>
        <Point T="1649559662267" X="285" Y="429"/>
        <Point T="1649559662299" X="286" Y="429"/>
        <Point T="1649559662339" X="287" Y="429"/>
    </Stroke>
</Gesture>
