<?xml version="1.0" encoding="utf-8" standalone="yes"?><Gesture Name="s~07" Subject="212" Speed="Medium" Number="7" NumPts="78" Milliseconds="160" AppName="GestureCollection" AppVer="0.0" Date="Wednesday, April 13, 2022" TimeOfDay="6:24:28 PM"><Stroke index="1"><Point X="679" Y="279" T="1649888423588" Pressure="128" /><Point X="677" Y="300" T="1649888423612" Pressure="128" /><Point X="676" Y="308" T="1649888423613" Pressure="128" /><Point X="674" Y="318" T="1649888423623" Pressure="128" /><Point X="671" Y="330" T="1649888423633" Pressure="128" /><Point X="668" Y="340" T="1649888423643" Pressure="128" /><Point X="663" Y="353" T="1649888423653" Pressure="128" /><Point X="659" Y="364" T="1649888423663" Pressure="128" /><Point X="654" Y="376" T="1649888423673" Pressure="128" /><Point X="650" Y="385" T="1649888423683" Pressure="128" /><Point X="644" Y="396" T="1649888423693" Pressure="128" /><Point X="637" Y="407" T="1649888423714" Pressure="128" /><Point X="630" Y="418" T="1649888423725" Pressure="128" /><Point X="621" Y="431" T="1649888423735" Pressure="128" /><Point X="611" Y="444" T="1649888423756" Pressure="128" /><Point X="600" Y="458" T="1649888423767" Pressure="128" /><Point X="590" Y="470" T="1649888423788" Pressure="128" /><Point X="579" Y="483" T="1649888423797" Pressure="128" /><Point X="569" Y="494" T="1649888423808" Pressure="128" /><Point X="558" Y="505" T="1649888423817" Pressure="128" /><Point X="550" Y="514" T="1649888423828" Pressure="128" /><Point X="543" Y="522" T="1649888423848" Pressure="128" /><Point X="535" Y="529" T="1649888423857" Pressure="128" /><Point X="529" Y="534" T="1649888423867" Pressure="128" /><Point X="523" Y="539" T="1649888423878" Pressure="128" /><Point X="518" Y="544" T="1649888423897" Pressure="128" /><Point X="513" Y="548" T="1649888423908" Pressure="128" /><Point X="513" Y="548" T="1649888423917" Pressure="128" /></Stroke><Stroke index="2"><Point X="488" Y="546" T="1649888423948" Pressure="128" /><Point X="498" Y="546" T="1649888423979" Pressure="128" /><Point X="507" Y="546" T="1649888424044" Pressure="128" /><Point X="518" Y="546" T="1649888425550" Pressure="128" /><Point X="531" Y="546" T="1649888425552" Pressure="128" /><Point X="545" Y="547" T="1649888425557" Pressure="128" /><Point X="560" Y="546" T="1649888425568" Pressure="128" /><Point X="579" Y="545" T="1649888425578" Pressure="128" /><Point X="596" Y="544" T="1649888425590" Pressure="128" /><Point X="614" Y="542" T="1649888425600" Pressure="128" /><Point X="633" Y="539" T="1649888425621" Pressure="128" /><Point X="652" Y="536" T="1649888425631" Pressure="128" /><Point X="668" Y="532" T="1649888425642" Pressure="128" /><Point X="684" Y="527" T="1649888425651" Pressure="128" /><Point X="699" Y="522" T="1649888425661" Pressure="128" /><Point X="712" Y="515" T="1649888425672" Pressure="128" /><Point X="724" Y="507" T="1649888425682" Pressure="128" /><Point X="734" Y="501" T="1649888425692" Pressure="128" /><Point X="741" Y="496" T="1649888425702" Pressure="128" /><Point X="748" Y="490" T="1649888425711" Pressure="128" /><Point X="753" Y="486" T="1649888425721" Pressure="128" /><Point X="756" Y="482" T="1649888425731" Pressure="128" /><Point X="759" Y="480" T="1649888425753" Pressure="128" /><Point X="761" Y="478" T="1649888425761" Pressure="128" /><Point X="763" Y="476" T="1649888425772" Pressure="128" /><Point X="764" Y="474" T="1649888425782" Pressure="128" /><Point X="765" Y="473" T="1649888425809" Pressure="128" /><Point X="766" Y="472" T="1649888425828" Pressure="128" /><Point X="767" Y="471" T="1649888425879" Pressure="128" /><Point X="768" Y="470" T="1649888425890" Pressure="128" /><Point X="768" Y="470" T="1649888425901" Pressure="128" /></Stroke><Stroke index="3"><Point X="757" Y="444" T="1649888425931" Pressure="128" /><Point X="763" Y="450" T="1649888425943" Pressure="128" /><Point X="769" Y="457" T="1649888425952" Pressure="128" /><Point X="775" Y="464" T="1649888425962" Pressure="128" /><Point X="781" Y="473" T="1649888425972" Pressure="128" /><Point X="787" Y="483" T="1649888425983" Pressure="128" /><Point X="791" Y="495" T="1649888426002" Pressure="128" /><Point X="794" Y="506" T="1649888426013" Pressure="128" /><Point X="796" Y="517" T="1649888426034" Pressure="128" /><Point X="798" Y="528" T="1649888426044" Pressure="128" /><Point X="799" Y="537" T="1649888426054" Pressure="128" /><Point X="800" Y="545" T="1649888426064" Pressure="128" /><Point X="801" Y="551" T="1649888426076" Pressure="128" /><Point X="802" Y="556" T="1649888426095" Pressure="128" /><Point X="804" Y="566" T="1649888426105" Pressure="128" /><Point X="805" Y="579" T="1649888426115" Pressure="128" /><Point X="805" Y="579" T="1649888426124" Pressure="128" /></Stroke></Gesture>