<?xml version="1.0" encoding="UTF-8" standalone="yes"?>
<Gesture AppName="PointClouds" AppVer="0.0.0.0" Date="Sunday, April 10, 2022" Millseconds="615" Name="eng~01" NumPts="56" Number="1" Speed="MEDIUM" Subject="6" TimeOfDay="11:18:57 PM">
<Stroke index="1">
<Point T="1649647136391" X="227" Y="304"/>
<Point T="1649647136439" X="227" Y="307"/>
<Point T="1649647136447" X="226" Y="310"/>
<Point T="1649647136453" X="224" Y="316"/>
<Point T="1649647136461" X="222" Y="321"/>
<Point T="1649647136469" X="218" Y="329"/>
<Point T="1649647136478" X="215" Y="337"/>
<Point T="1649647136484" X="213" Y="347"/>
<Point T="1649647136501" X="203" Y="371"/>
<Point T="1649647136509" X="196" Y="379"/>
<Point T="1649647136517" X="190" Y="388"/>
<Point T="1649647136524" X="185" Y="397"/>
<Point T="1649647136533" X="181" Y="405"/>
<Point T="1649647136539" X="179" Y="413"/>
<Point T="1649647136548" X="174" Y="422"/>
<Point T="1649647136554" X="167" Y="431"/>
<Point T="1649647136563" X="164" Y="439"/>
<Point T="1649647136570" X="161" Y="447"/>
<Point T="1649647136579" X="159" Y="456"/>
<Point T="1649647136585" X="157" Y="463"/>
<Point T="1649647136593" X="155" Y="469"/>
<Point T="1649647136600" X="152" Y="474"/>
<Point T="1649647136608" X="150" Y="480"/>
<Point T="1649647136616" X="148" Y="486"/>
<Point T="1649647136624" X="146" Y="491"/>
<Point T="1649647136633" X="145" Y="494"/>
<Point T="1649647136640" X="144" Y="498"/>
<Point T="1649647136648" X="143" Y="501"/>
<Point T="1649647136655" X="143" Y="504"/>
<Point T="1649647136663" X="142" Y="506"/>
<Point T="1649647136670" X="142" Y="507"/>
<Point T="1649647136679" X="142" Y="508"/>
<Point T="1649647136689" X="142" Y="509"/>
<Point T="1649647136695" X="142" Y="510"/>
<Point T="1649647136701" X="142" Y="511"/>
<Point T="1649647136853" X="143" Y="511"/>
<Point T="1649647136860" X="150" Y="513"/>
<Point T="1649647136867" X="160" Y="515"/>
<Point T="1649647136875" X="174" Y="517"/>
<Point T="1649647136883" X="190" Y="519"/>
<Point T="1649647136890" X="204" Y="520"/>
<Point T="1649647136898" X="218" Y="521"/>
<Point T="1649647136908" X="231" Y="521"/>
<Point T="1649647136915" X="245" Y="521"/>
<Point T="1649647136921" X="255" Y="521"/>
<Point T="1649647136929" X="263" Y="521"/>
<Point T="1649647136938" X="271" Y="521"/>
<Point T="1649647136945" X="277" Y="521"/>
<Point T="1649647136953" X="281" Y="521"/>
<Point T="1649647136960" X="284" Y="521"/>
<Point T="1649647136968" X="286" Y="522"/>
<Point T="1649647136974" X="288" Y="522"/>
<Point T="1649647136984" X="291" Y="523"/>
<Point T="1649647136990" X="293" Y="523"/>
<Point T="1649647136999" X="294" Y="524"/>
<Point T="1649647137006" X="295" Y="524"/>
</Stroke>
</Gesture>
