<?xml version="1.0" encoding="UTF-8" standalone="yes"?>
<Gesture AppName="PointClouds" AppVer="0.0.0.0" Date="Sunday, April 10, 2022" Millseconds="1381" Name="ts~04" NumPts="87" Number="4" Speed="MEDIUM" Subject="6" TimeOfDay="11:28:59 PM">
<Stroke index="1">
<Point T="1649647736673" X="140" Y="302"/>
<Point T="1649647736739" X="140" Y="303"/>
<Point T="1649647736751" X="142" Y="304"/>
<Point T="1649647736760" X="150" Y="304"/>
<Point T="1649647736769" X="162" Y="304"/>
<Point T="1649647736776" X="174" Y="302"/>
<Point T="1649647736784" X="188" Y="300"/>
<Point T="1649647736792" X="201" Y="298"/>
<Point T="1649647736800" X="214" Y="297"/>
<Point T="1649647736806" X="229" Y="294"/>
<Point T="1649647736815" X="245" Y="292"/>
<Point T="1649647736822" X="265" Y="291"/>
<Point T="1649647736830" X="285" Y="289"/>
<Point T="1649647736839" X="298" Y="288"/>
<Point T="1649647736846" X="306" Y="288"/>
<Point T="1649647736854" X="313" Y="288"/>
<Point T="1649647736860" X="316" Y="288"/>
<Point T="1649647736869" X="317" Y="288"/>
</Stroke>
<Stroke index="2">
<Point T="1649647737320" X="224" Y="256"/>
<Point T="1649647737332" X="224" Y="257"/>
<Point T="1649647737340" X="224" Y="262"/>
<Point T="1649647737350" X="224" Y="267"/>
<Point T="1649647737354" X="223" Y="273"/>
<Point T="1649647737361" X="221" Y="281"/>
<Point T="1649647737369" X="219" Y="289"/>
<Point T="1649647737378" X="214" Y="299"/>
<Point T="1649647737385" X="207" Y="312"/>
<Point T="1649647737394" X="200" Y="327"/>
<Point T="1649647737401" X="194" Y="337"/>
<Point T="1649647737409" X="187" Y="346"/>
<Point T="1649647737416" X="181" Y="354"/>
<Point T="1649647737424" X="175" Y="360"/>
<Point T="1649647737432" X="170" Y="369"/>
<Point T="1649647737440" X="166" Y="375"/>
<Point T="1649647737448" X="164" Y="380"/>
<Point T="1649647737455" X="163" Y="386"/>
<Point T="1649647737462" X="161" Y="391"/>
<Point T="1649647737470" X="160" Y="392"/>
<Point T="1649647737479" X="159" Y="393"/>
<Point T="1649647737485" X="158" Y="395"/>
<Point T="1649647737494" X="158" Y="396"/>
<Point T="1649647737594" X="158" Y="397"/>
<Point T="1649647737609" X="159" Y="397"/>
<Point T="1649647737618" X="168" Y="397"/>
<Point T="1649647737624" X="180" Y="397"/>
<Point T="1649647737633" X="195" Y="396"/>
<Point T="1649647737639" X="217" Y="395"/>
<Point T="1649647737647" X="238" Y="392"/>
<Point T="1649647737656" X="261" Y="389"/>
<Point T="1649647737663" X="276" Y="387"/>
<Point T="1649647737672" X="290" Y="384"/>
<Point T="1649647737680" X="299" Y="383"/>
<Point T="1649647737685" X="306" Y="381"/>
<Point T="1649647737695" X="312" Y="380"/>
<Point T="1649647737702" X="315" Y="380"/>
<Point T="1649647737710" X="316" Y="380"/>
<Point T="1649647737719" X="317" Y="380"/>
<Point T="1649647737831" X="317" Y="381"/>
<Point T="1649647737839" X="315" Y="384"/>
<Point T="1649647737845" X="314" Y="386"/>
<Point T="1649647737851" X="312" Y="390"/>
<Point T="1649647737860" X="310" Y="395"/>
<Point T="1649647737868" X="309" Y="398"/>
<Point T="1649647737876" X="307" Y="401"/>
<Point T="1649647737884" X="305" Y="407"/>
<Point T="1649647737891" X="303" Y="413"/>
<Point T="1649647737899" X="300" Y="419"/>
<Point T="1649647737905" X="297" Y="424"/>
<Point T="1649647737914" X="294" Y="432"/>
<Point T="1649647737921" X="291" Y="437"/>
<Point T="1649647737930" X="287" Y="444"/>
<Point T="1649647737939" X="285" Y="448"/>
<Point T="1649647737946" X="283" Y="451"/>
<Point T="1649647737953" X="280" Y="455"/>
<Point T="1649647737959" X="279" Y="459"/>
<Point T="1649647737968" X="277" Y="463"/>
<Point T="1649647737976" X="275" Y="467"/>
<Point T="1649647737984" X="273" Y="473"/>
<Point T="1649647737991" X="271" Y="479"/>
<Point T="1649647737999" X="269" Y="485"/>
<Point T="1649647738009" X="268" Y="488"/>
<Point T="1649647738014" X="266" Y="490"/>
<Point T="1649647738021" X="265" Y="492"/>
<Point T="1649647738030" X="263" Y="493"/>
<Point T="1649647738039" X="262" Y="494"/>
<Point T="1649647738046" X="261" Y="495"/>
<Point T="1649647738054" X="261" Y="496"/>
</Stroke>
</Gesture>
