<?xml version="1.0" encoding="UTF-8" standalone="yes"?>
<Gesture AppName="PointClouds" AppVer="0.0.0.0" Date="Saturday, April 09, 2022" Millseconds="872" Name="s~01" NumPts="74" Number="1" Speed="MEDIUM" Subject="1" TimeOfDay="8:31:54 PM">
    <Stroke index="1">
        <Point T="1649550712323" X="259" Y="355"/>
        <Point T="1649550712348" X="258" Y="357"/>
        <Point T="1649550712371" X="258" Y="358"/>
        <Point T="1649550712380" X="246" Y="375"/>
        <Point T="1649550712381" X="246" Y="376"/>
        <Point T="1649550712389" X="239" Y="385"/>
        <Point T="1649550712394" X="236" Y="389"/>
        <Point T="1649550712395" X="234" Y="391"/>
        <Point T="1649550712399" X="231" Y="394"/>
        <Point T="1649550712400" X="230" Y="395"/>
        <Point T="1649550712408" X="229" Y="396"/>
        <Point T="1649550712414" X="219" Y="409"/>
        <Point T="1649550712421" X="214" Y="414"/>
        <Point T="1649550712439" X="199" Y="431"/>
        <Point T="1649550712450" X="192" Y="439"/>
        <Point T="1649550712456" X="189" Y="442"/>
        <Point T="1649550712462" X="186" Y="445"/>
        <Point T="1649550712466" X="185" Y="447"/>
        <Point T="1649550712466" X="184" Y="447"/>
        <Point T="1649550712472" X="182" Y="449"/>
        <Point T="1649550712478" X="180" Y="451"/>
        <Point T="1649550712485" X="178" Y="453"/>
        <Point T="1649550712495" X="175" Y="457"/>
        <Point T="1649550712501" X="174" Y="458"/>
        <Point T="1649550712511" X="173" Y="460"/>
        <Point T="1649550712515" X="172" Y="460"/>
        <Point T="1649550712521" X="172" Y="461"/>
        <Point T="1649550712580" X="173" Y="461"/>
        <Point T="1649550712594" X="175" Y="462"/>
        <Point T="1649550712594" X="177" Y="462"/>
        <Point T="1649550712601" X="180" Y="462"/>
        <Point T="1649550712605" X="182" Y="462"/>
        <Point T="1649550712612" X="192" Y="461"/>
        <Point T="1649550712618" X="196" Y="461"/>
        <Point T="1649550712624" X="206" Y="461"/>
        <Point T="1649550712625" X="208" Y="461"/>
        <Point T="1649550712633" X="222" Y="460"/>
        <Point T="1649550712635" X="224" Y="460"/>
        <Point T="1649550712640" X="238" Y="459"/>
        <Point T="1649550712647" X="257" Y="458"/>
        <Point T="1649550712657" X="286" Y="457"/>
        <Point T="1649550712663" X="304" Y="456"/>
        <Point T="1649550712664" X="306" Y="456"/>
        <Point T="1649550712672" X="327" Y="455"/>
        <Point T="1649550712683" X="348" Y="454"/>
        <Point T="1649550712688" X="349" Y="454"/>
        <Point T="1649550712693" X="359" Y="454"/>
        <Point T="1649550712705" X="365" Y="453"/>
        <Point T="1649550712713" X="366" Y="453"/>
        <Point T="1649550712716" X="367" Y="453"/>
    </Stroke>
    <Stroke index="2">
        <Point T="1649550712989" X="328" Y="434"/>
        <Point T="1649550713020" X="328" Y="435"/>
        <Point T="1649550713024" X="329" Y="436"/>
        <Point T="1649550713031" X="330" Y="437"/>
        <Point T="1649550713037" X="330" Y="438"/>
        <Point T="1649550713041" X="333" Y="439"/>
        <Point T="1649550713045" X="334" Y="441"/>
        <Point T="1649550713048" X="335" Y="442"/>
        <Point T="1649550713052" X="336" Y="442"/>
        <Point T="1649550713058" X="341" Y="446"/>
        <Point T="1649550713059" X="342" Y="446"/>
        <Point T="1649550713062" X="343" Y="447"/>
        <Point T="1649550713065" X="345" Y="448"/>
        <Point T="1649550713070" X="347" Y="450"/>
        <Point T="1649550713071" X="349" Y="451"/>
        <Point T="1649550713077" X="355" Y="455"/>
        <Point T="1649550713082" X="359" Y="458"/>
        <Point T="1649550713093" X="366" Y="463"/>
        <Point T="1649550713097" X="368" Y="464"/>
        <Point T="1649550713100" X="370" Y="465"/>
        <Point T="1649550713115" X="376" Y="470"/>
        <Point T="1649550713127" X="379" Y="472"/>
        <Point T="1649550713136" X="380" Y="473"/>
        <Point T="1649550713195" X="379" Y="473"/>
    </Stroke>
</Gesture>
