<?xml version="1.0" encoding="UTF-8" standalone="yes"?>
<Gesture AppName="PointClouds" AppVer="0.0.0.0" Date="Sunday, April 10, 2022" Millseconds="1547" Name="f~08" NumPts="75" Number="8" Speed="MEDIUM" Subject="3" TimeOfDay="9:37:29 PM">
    <Stroke index="1">
        <Point T="1649641046904" X="154" Y="388"/>
        <Point T="1649641046936" X="171" Y="388"/>
        <Point T="1649641046943" X="177" Y="387"/>
        <Point T="1649641046966" X="283" Y="387"/>
        <Point T="1649641046972" X="302" Y="388"/>
        <Point T="1649641046979" X="319" Y="390"/>
        <Point T="1649641046987" X="334" Y="391"/>
        <Point T="1649641046994" X="346" Y="393"/>
        <Point T="1649641047009" X="360" Y="394"/>
        <Point T="1649641047019" X="370" Y="396"/>
        <Point T="1649641047024" X="375" Y="396"/>
        <Point T="1649641047033" X="377" Y="396"/>
        <Point T="1649641047039" X="380" Y="396"/>
        <Point T="1649641047054" X="381" Y="396"/>
    </Stroke>
    <Stroke index="2">
        <Point T="1649641047790" X="207" Y="394"/>
        <Point T="1649641047828" X="207" Y="395"/>
        <Point T="1649641047858" X="207" Y="397"/>
        <Point T="1649641047872" X="207" Y="399"/>
        <Point T="1649641047880" X="207" Y="400"/>
        <Point T="1649641047887" X="207" Y="401"/>
        <Point T="1649641047895" X="207" Y="402"/>
        <Point T="1649641047902" X="207" Y="405"/>
        <Point T="1649641047909" X="207" Y="406"/>
        <Point T="1649641047919" X="207" Y="410"/>
        <Point T="1649641047924" X="207" Y="415"/>
        <Point T="1649641047948" X="207" Y="421"/>
        <Point T="1649641047950" X="207" Y="427"/>
        <Point T="1649641047954" X="207" Y="433"/>
        <Point T="1649641047962" X="207" Y="439"/>
        <Point T="1649641047969" X="206" Y="451"/>
        <Point T="1649641047977" X="205" Y="457"/>
        <Point T="1649641047985" X="205" Y="462"/>
        <Point T="1649641047991" X="205" Y="469"/>
        <Point T="1649641048001" X="205" Y="472"/>
        <Point T="1649641048007" X="205" Y="477"/>
        <Point T="1649641048014" X="205" Y="479"/>
        <Point T="1649641048021" X="205" Y="481"/>
        <Point T="1649641048029" X="205" Y="483"/>
        <Point T="1649641048037" X="206" Y="484"/>
        <Point T="1649641048044" X="206" Y="486"/>
        <Point T="1649641048052" X="207" Y="486"/>
        <Point T="1649641048059" X="207" Y="487"/>
        <Point T="1649641048068" X="208" Y="488"/>
        <Point T="1649641048074" X="209" Y="489"/>
        <Point T="1649641048090" X="212" Y="491"/>
        <Point T="1649641048097" X="214" Y="493"/>
        <Point T="1649641048104" X="222" Y="495"/>
        <Point T="1649641048112" X="228" Y="497"/>
        <Point T="1649641048119" X="234" Y="498"/>
        <Point T="1649641048127" X="244" Y="501"/>
        <Point T="1649641048135" X="254" Y="503"/>
        <Point T="1649641048141" X="267" Y="506"/>
        <Point T="1649641048151" X="277" Y="508"/>
        <Point T="1649641048157" X="286" Y="509"/>
        <Point T="1649641048166" X="296" Y="510"/>
        <Point T="1649641048172" X="299" Y="511"/>
        <Point T="1649641048179" X="303" Y="511"/>
        <Point T="1649641048187" X="306" Y="512"/>
        <Point T="1649641048203" X="308" Y="512"/>
        <Point T="1649641048209" X="309" Y="512"/>
        <Point T="1649641048224" X="310" Y="511"/>
        <Point T="1649641048240" X="311" Y="511"/>
        <Point T="1649641048246" X="313" Y="510"/>
        <Point T="1649641048254" X="316" Y="509"/>
        <Point T="1649641048261" X="323" Y="506"/>
        <Point T="1649641048269" X="331" Y="506"/>
        <Point T="1649641048277" X="345" Y="506"/>
        <Point T="1649641048285" X="354" Y="506"/>
        <Point T="1649641048292" X="360" Y="506"/>
        <Point T="1649641048307" X="366" Y="508"/>
        <Point T="1649641048316" X="370" Y="508"/>
        <Point T="1649641048322" X="373" Y="509"/>
        <Point T="1649641048330" X="375" Y="510"/>
        <Point T="1649641048336" X="376" Y="510"/>
        <Point T="1649641048451" X="375" Y="510"/>
    </Stroke>
</Gesture>
