<?xml version="1.0" encoding="UTF-8" standalone="yes"?>
<Gesture AppName="PointClouds" AppVer="0.0.0.0" Date="Monday, April 11, 2022" Millseconds="2656" Name="d~08" NumPts="169" Number="8" Speed="MEDIUM" Subject="5" TimeOfDay="11:46:17 AM">
<Stroke index="1">
<Point T="1649699173998" X="251" Y="227"/>
<Point T="1649699174005" X="250" Y="228"/>
<Point T="1649699174035" X="249" Y="229"/>
<Point T="1649699174040" X="249" Y="230"/>
<Point T="1649699174047" X="248" Y="231"/>
<Point T="1649699174054" X="247" Y="233"/>
<Point T="1649699174061" X="245" Y="236"/>
<Point T="1649699174068" X="243" Y="240"/>
<Point T="1649699174075" X="239" Y="244"/>
<Point T="1649699174083" X="236" Y="250"/>
<Point T="1649699174089" X="232" Y="256"/>
<Point T="1649699174097" X="228" Y="262"/>
<Point T="1649699174103" X="221" Y="271"/>
<Point T="1649699174110" X="217" Y="278"/>
<Point T="1649699174117" X="213" Y="284"/>
<Point T="1649699174124" X="208" Y="292"/>
<Point T="1649699174131" X="202" Y="299"/>
<Point T="1649699174138" X="199" Y="305"/>
<Point T="1649699174146" X="195" Y="311"/>
<Point T="1649699174153" X="191" Y="317"/>
<Point T="1649699174163" X="189" Y="321"/>
<Point T="1649699174166" X="185" Y="326"/>
<Point T="1649699174173" X="185" Y="327"/>
<Point T="1649699174179" X="184" Y="329"/>
<Point T="1649699174186" X="183" Y="330"/>
<Point T="1649699174194" X="182" Y="330"/>
<Point T="1649699174264" X="184" Y="330"/>
<Point T="1649699174271" X="190" Y="329"/>
<Point T="1649699174278" X="197" Y="326"/>
<Point T="1649699174286" X="205" Y="325"/>
<Point T="1649699174292" X="217" Y="322"/>
<Point T="1649699174300" X="233" Y="320"/>
<Point T="1649699174306" X="246" Y="318"/>
<Point T="1649699174313" X="259" Y="318"/>
<Point T="1649699174320" X="271" Y="318"/>
<Point T="1649699174327" X="281" Y="319"/>
<Point T="1649699174334" X="291" Y="319"/>
<Point T="1649699174341" X="301" Y="320"/>
<Point T="1649699174347" X="308" Y="320"/>
<Point T="1649699174355" X="315" Y="321"/>
<Point T="1649699174363" X="322" Y="321"/>
<Point T="1649699174368" X="327" Y="322"/>
<Point T="1649699174377" X="331" Y="322"/>
<Point T="1649699174382" X="335" Y="323"/>
<Point T="1649699174390" X="336" Y="323"/>
<Point T="1649699174396" X="337" Y="323"/>
<Point T="1649699174403" X="338" Y="324"/>
<Point T="1649699174453" X="338" Y="326"/>
<Point T="1649699174460" X="337" Y="328"/>
<Point T="1649699174466" X="336" Y="330"/>
<Point T="1649699174474" X="334" Y="332"/>
<Point T="1649699174480" X="330" Y="336"/>
<Point T="1649699174488" X="326" Y="340"/>
<Point T="1649699174495" X="323" Y="344"/>
<Point T="1649699174503" X="319" Y="350"/>
<Point T="1649699174508" X="316" Y="354"/>
<Point T="1649699174515" X="312" Y="362"/>
<Point T="1649699174522" X="309" Y="371"/>
<Point T="1649699174530" X="306" Y="378"/>
<Point T="1649699174535" X="304" Y="385"/>
<Point T="1649699174542" X="301" Y="392"/>
<Point T="1649699174549" X="300" Y="399"/>
<Point T="1649699174557" X="299" Y="403"/>
<Point T="1649699174564" X="298" Y="407"/>
<Point T="1649699174571" X="297" Y="410"/>
<Point T="1649699174579" X="296" Y="413"/>
<Point T="1649699174584" X="296" Y="415"/>
<Point T="1649699174592" X="296" Y="416"/>
<Point T="1649699174598" X="296" Y="417"/>
<Point T="1649699174606" X="295" Y="418"/>
<Point T="1649699174620" X="294" Y="418"/>
<Point T="1649699174635" X="293" Y="418"/>
<Point T="1649699174649" X="291" Y="418"/>
<Point T="1649699174657" X="289" Y="418"/>
<Point T="1649699174662" X="285" Y="418"/>
<Point T="1649699174669" X="280" Y="415"/>
<Point T="1649699174676" X="275" Y="413"/>
<Point T="1649699174683" X="267" Y="408"/>
<Point T="1649699174689" X="261" Y="403"/>
<Point T="1649699174697" X="254" Y="396"/>
<Point T="1649699174704" X="249" Y="390"/>
<Point T="1649699174711" X="243" Y="387"/>
<Point T="1649699174718" X="240" Y="383"/>
<Point T="1649699174724" X="237" Y="380"/>
<Point T="1649699174733" X="234" Y="377"/>
<Point T="1649699174738" X="232" Y="375"/>
<Point T="1649699174745" X="231" Y="373"/>
<Point T="1649699174752" X="230" Y="371"/>
<Point T="1649699174759" X="230" Y="370"/>
<Point T="1649699174766" X="230" Y="368"/>
<Point T="1649699174774" X="229" Y="368"/>
<Point T="1649699174788" X="228" Y="367"/>
<Point T="1649699174796" X="228" Y="366"/>
<Point T="1649699174816" X="228" Y="365"/>
</Stroke>
<Stroke index="2">
<Point T="1649699175775" X="249" Y="313"/>
<Point T="1649699175780" X="248" Y="313"/>
<Point T="1649699175850" X="247" Y="313"/>
<Point T="1649699175879" X="246" Y="313"/>
<Point T="1649699175900" X="246" Y="314"/>
<Point T="1649699175907" X="244" Y="316"/>
<Point T="1649699175912" X="242" Y="318"/>
<Point T="1649699175921" X="240" Y="321"/>
<Point T="1649699175926" X="237" Y="325"/>
<Point T="1649699175933" X="235" Y="328"/>
<Point T="1649699175940" X="233" Y="331"/>
<Point T="1649699175947" X="232" Y="334"/>
<Point T="1649699175953" X="230" Y="337"/>
<Point T="1649699175961" X="228" Y="338"/>
<Point T="1649699175968" X="227" Y="339"/>
<Point T="1649699175975" X="227" Y="340"/>
<Point T="1649699175983" X="226" Y="341"/>
<Point T="1649699175989" X="224" Y="342"/>
<Point T="1649699175996" X="223" Y="344"/>
<Point T="1649699176003" X="222" Y="346"/>
<Point T="1649699176010" X="221" Y="346"/>
<Point T="1649699176017" X="220" Y="348"/>
<Point T="1649699176024" X="219" Y="350"/>
<Point T="1649699176031" X="217" Y="351"/>
<Point T="1649699176047" X="217" Y="352"/>
<Point T="1649699176053" X="216" Y="353"/>
<Point T="1649699176059" X="215" Y="354"/>
<Point T="1649699176073" X="214" Y="354"/>
<Point T="1649699176087" X="214" Y="355"/>
<Point T="1649699176102" X="213" Y="356"/>
<Point T="1649699176116" X="212" Y="356"/>
<Point T="1649699176123" X="212" Y="357"/>
<Point T="1649699176129" X="211" Y="359"/>
<Point T="1649699176136" X="208" Y="362"/>
<Point T="1649699176143" X="205" Y="363"/>
<Point T="1649699176149" X="203" Y="366"/>
<Point T="1649699176156" X="201" Y="368"/>
<Point T="1649699176164" X="200" Y="371"/>
<Point T="1649699176170" X="198" Y="372"/>
<Point T="1649699176177" X="197" Y="372"/>
<Point T="1649699176184" X="196" Y="373"/>
<Point T="1649699176191" X="196" Y="374"/>
<Point T="1649699176199" X="195" Y="374"/>
<Point T="1649699176206" X="195" Y="375"/>
<Point T="1649699176212" X="194" Y="375"/>
<Point T="1649699176240" X="193" Y="376"/>
<Point T="1649699176255" X="193" Y="377"/>
<Point T="1649699176261" X="192" Y="377"/>
<Point T="1649699176275" X="191" Y="377"/>
<Point T="1649699176282" X="191" Y="378"/>
<Point T="1649699176297" X="191" Y="379"/>
<Point T="1649699176304" X="190" Y="379"/>
<Point T="1649699176312" X="190" Y="380"/>
<Point T="1649699176326" X="189" Y="380"/>
<Point T="1649699176339" X="189" Y="381"/>
<Point T="1649699176360" X="189" Y="382"/>
<Point T="1649699176388" X="188" Y="383"/>
<Point T="1649699176395" X="188" Y="384"/>
<Point T="1649699176401" X="187" Y="385"/>
<Point T="1649699176408" X="186" Y="385"/>
<Point T="1649699176423" X="185" Y="386"/>
<Point T="1649699176429" X="184" Y="387"/>
<Point T="1649699176444" X="184" Y="388"/>
<Point T="1649699176451" X="184" Y="389"/>
<Point T="1649699176457" X="183" Y="389"/>
<Point T="1649699176464" X="183" Y="390"/>
<Point T="1649699176471" X="182" Y="390"/>
<Point T="1649699176486" X="181" Y="391"/>
<Point T="1649699176498" X="181" Y="392"/>
<Point T="1649699176534" X="181" Y="393"/>
<Point T="1649699176548" X="181" Y="394"/>
<Point T="1649699176561" X="180" Y="394"/>
<Point T="1649699176576" X="179" Y="395"/>
<Point T="1649699176633" X="179" Y="396"/>
<Point T="1649699176654" X="179" Y="397"/>
</Stroke>
</Gesture>
