<?xml version="1.0" encoding="utf-8" standalone="yes"?><Gesture Name="g~01" Subject="294" Speed="Medium" Number="1" NumPts="90" Milliseconds="523" AppName="GestureCollection" AppVer="0.0" Date="Wednesday, April 13, 2022" TimeOfDay="2:19:12 PM"><Stroke index="1"><Point X="618" Y="219" T="1649873869342" Pressure="128" /><Point X="609" Y="234" T="1649873869344" Pressure="128" /><Point X="606" Y="240" T="1649873869345" Pressure="128" /><Point X="602" Y="247" T="1649873869353" Pressure="128" /><Point X="598" Y="253" T="1649873869362" Pressure="128" /><Point X="594" Y="259" T="1649873869371" Pressure="128" /><Point X="591" Y="265" T="1649873869379" Pressure="128" /><Point X="587" Y="272" T="1649873869389" Pressure="128" /><Point X="583" Y="277" T="1649873869403" Pressure="128" /><Point X="580" Y="282" T="1649873869406" Pressure="128" /><Point X="578" Y="285" T="1649873869418" Pressure="128" /><Point X="576" Y="288" T="1649873869424" Pressure="128" /><Point X="574" Y="290" T="1649873869433" Pressure="128" /><Point X="573" Y="291" T="1649873869441" Pressure="128" /><Point X="572" Y="292" T="1649873869450" Pressure="128" /><Point X="572" Y="293" T="1649873869458" Pressure="128" /><Point X="571" Y="293" T="1649873869467" Pressure="128" /><Point X="571" Y="294" T="1649873869476" Pressure="128" /><Point X="570" Y="294" T="1649873869484" Pressure="128" /><Point X="570" Y="295" T="1649873869493" Pressure="128" /><Point X="570" Y="296" T="1649873869502" Pressure="128" /><Point X="571" Y="298" T="1649873869511" Pressure="128" /><Point X="572" Y="301" T="1649873869520" Pressure="128" /><Point X="573" Y="305" T="1649873869528" Pressure="128" /><Point X="574" Y="309" T="1649873869537" Pressure="128" /><Point X="576" Y="313" T="1649873869545" Pressure="128" /><Point X="578" Y="318" T="1649873869554" Pressure="128" /><Point X="580" Y="324" T="1649873869562" Pressure="128" /><Point X="582" Y="330" T="1649873869572" Pressure="128" /><Point X="583" Y="336" T="1649873869582" Pressure="128" /><Point X="585" Y="340" T="1649873869591" Pressure="128" /><Point X="587" Y="344" T="1649873869600" Pressure="128" /><Point X="588" Y="348" T="1649873869608" Pressure="128" /><Point X="590" Y="352" T="1649873869617" Pressure="128" /><Point X="591" Y="357" T="1649873869643" Pressure="128" /><Point X="593" Y="360" T="1649873869686" Pressure="128" /><Point X="594" Y="363" T="1649873869696" Pressure="128" /><Point X="595" Y="366" T="1649873870584" Pressure="128" /><Point X="595" Y="367" T="1649873870586" Pressure="128" /><Point X="596" Y="369" T="1649873870591" Pressure="128" /><Point X="596" Y="370" T="1649873870600" Pressure="128" /><Point X="597" Y="371" T="1649873870610" Pressure="128" /><Point X="597" Y="372" T="1649873870618" Pressure="128" /><Point X="597" Y="373" T="1649873870627" Pressure="128" /><Point X="598" Y="373" T="1649873870636" Pressure="128" /><Point X="598" Y="373" T="1649873870644" Pressure="128" /></Stroke><Stroke index="2"><Point X="656" Y="246" T="1649873870661" Pressure="128" /><Point X="652" Y="252" T="1649873870671" Pressure="128" /><Point X="648" Y="257" T="1649873870680" Pressure="128" /><Point X="643" Y="262" T="1649873870689" Pressure="128" /><Point X="639" Y="268" T="1649873870698" Pressure="128" /><Point X="635" Y="273" T="1649873870708" Pressure="128" /><Point X="632" Y="278" T="1649873870716" Pressure="128" /><Point X="630" Y="282" T="1649873870725" Pressure="128" /><Point X="628" Y="284" T="1649873870734" Pressure="128" /><Point X="626" Y="287" T="1649873870744" Pressure="128" /><Point X="625" Y="288" T="1649873870752" Pressure="128" /><Point X="624" Y="290" T="1649873870770" Pressure="128" /><Point X="624" Y="291" T="1649873870788" Pressure="128" /><Point X="623" Y="292" T="1649873870842" Pressure="128" /><Point X="623" Y="293" T="1649873870896" Pressure="128" /><Point X="623" Y="294" T="1649873870963" Pressure="128" /><Point X="622" Y="294" T="1649873870972" Pressure="128" /><Point X="622" Y="295" T="1649873870981" Pressure="128" /><Point X="622" Y="296" T="1649873870991" Pressure="128" /><Point X="622" Y="299" T="1649873871000" Pressure="128" /><Point X="623" Y="302" T="1649873871009" Pressure="128" /><Point X="624" Y="307" T="1649873871018" Pressure="128" /><Point X="625" Y="311" T="1649873871026" Pressure="128" /><Point X="626" Y="316" T="1649873871035" Pressure="128" /><Point X="628" Y="323" T="1649873871045" Pressure="128" /><Point X="630" Y="330" T="1649873871055" Pressure="128" /><Point X="633" Y="336" T="1649873871066" Pressure="128" /><Point X="635" Y="341" T="1649873871074" Pressure="128" /><Point X="638" Y="347" T="1649873871083" Pressure="128" /><Point X="640" Y="352" T="1649873871091" Pressure="128" /><Point X="643" Y="357" T="1649873871101" Pressure="128" /><Point X="645" Y="361" T="1649873871109" Pressure="128" /><Point X="647" Y="365" T="1649873871118" Pressure="128" /><Point X="648" Y="368" T="1649873871126" Pressure="128" /><Point X="649" Y="370" T="1649873871136" Pressure="128" /><Point X="650" Y="371" T="1649873871145" Pressure="128" /><Point X="651" Y="373" T="1649873871154" Pressure="128" /><Point X="651" Y="374" T="1649873871168" Pressure="128" /><Point X="652" Y="375" T="1649873871173" Pressure="128" /><Point X="652" Y="376" T="1649873871183" Pressure="128" /><Point X="653" Y="376" T="1649873871191" Pressure="128" /><Point X="653" Y="377" T="1649873871201" Pressure="128" /><Point X="653" Y="377" T="1649873871211" Pressure="128" /></Stroke></Gesture>