<?xml version="1.0" encoding="utf-8" standalone="yes"?><Gesture Name="m~10" Subject="171" Speed="Medium" Number="10" NumPts="65" Milliseconds="676" AppName="GestureCollection" AppVer="0.0" Date="Wednesday, April 13, 2022" TimeOfDay="7:54:27 PM"><Stroke index="1"><Point X="711" Y="432" T="1649871764231" Pressure="128" /><Point X="702" Y="406" T="1649871764233" Pressure="128" /><Point X="701" Y="399" T="1649871764237" Pressure="128" /><Point X="700" Y="391" T="1649871764247" Pressure="128" /><Point X="698" Y="384" T="1649871764257" Pressure="128" /><Point X="698" Y="377" T="1649871764267" Pressure="128" /><Point X="697" Y="371" T="1649871764276" Pressure="128" /><Point X="697" Y="364" T="1649871764283" Pressure="128" /><Point X="697" Y="359" T="1649871764293" Pressure="128" /><Point X="697" Y="354" T="1649871764303" Pressure="128" /><Point X="697" Y="351" T="1649871764313" Pressure="128" /><Point X="697" Y="348" T="1649871764323" Pressure="128" /><Point X="697" Y="346" T="1649871764331" Pressure="128" /><Point X="697" Y="345" T="1649871764341" Pressure="128" /><Point X="697" Y="344" T="1649871764351" Pressure="128" /><Point X="697" Y="343" T="1649871764361" Pressure="128" /><Point X="697" Y="342" T="1649871764369" Pressure="128" /><Point X="697" Y="341" T="1649871764379" Pressure="128" /><Point X="697" Y="340" T="1649871764389" Pressure="128" /><Point X="698" Y="339" T="1649871764399" Pressure="128" /><Point X="702" Y="339" T="1649871764409" Pressure="128" /><Point X="707" Y="338" T="1649871764417" Pressure="128" /><Point X="714" Y="338" T="1649871764427" Pressure="128" /><Point X="722" Y="337" T="1649871764437" Pressure="128" /><Point X="730" Y="338" T="1649871764447" Pressure="128" /><Point X="741" Y="338" T="1649871764457" Pressure="128" /><Point X="752" Y="338" T="1649871764465" Pressure="128" /><Point X="761" Y="338" T="1649871764473" Pressure="128" /><Point X="770" Y="337" T="1649871764483" Pressure="128" /><Point X="779" Y="337" T="1649871764493" Pressure="128" /><Point X="788" Y="337" T="1649871764511" Pressure="128" /><Point X="797" Y="337" T="1649871764557" Pressure="128" /><Point X="804" Y="337" T="1649871764595" Pressure="128" /><Point X="811" Y="337" T="1649871764641" Pressure="128" /><Point X="818" Y="338" T="1649871764977" Pressure="128" /><Point X="825" Y="338" T="1649871765125" Pressure="128" /><Point X="830" Y="338" T="1649871765173" Pressure="128" /><Point X="835" Y="339" T="1649871765267" Pressure="128" /><Point X="838" Y="339" T="1649871765275" Pressure="128" /><Point X="840" Y="339" T="1649871765285" Pressure="128" /><Point X="842" Y="340" T="1649871765295" Pressure="128" /><Point X="843" Y="340" T="1649871765305" Pressure="128" /><Point X="844" Y="341" T="1649871765313" Pressure="128" /><Point X="845" Y="341" T="1649871765323" Pressure="128" /><Point X="846" Y="341" T="1649871765333" Pressure="128" /><Point X="847" Y="341" T="1649871765341" Pressure="128" /><Point X="847" Y="342" T="1649871765351" Pressure="128" /><Point X="848" Y="342" T="1649871765361" Pressure="128" /><Point X="848" Y="343" T="1649871765371" Pressure="128" /><Point X="849" Y="343" T="1649871765379" Pressure="128" /><Point X="849" Y="344" T="1649871765389" Pressure="128" /><Point X="849" Y="346" T="1649871765397" Pressure="128" /><Point X="849" Y="350" T="1649871765407" Pressure="128" /><Point X="849" Y="355" T="1649871765417" Pressure="128" /><Point X="849" Y="362" T="1649871765425" Pressure="128" /><Point X="849" Y="372" T="1649871765435" Pressure="128" /><Point X="849" Y="382" T="1649871765445" Pressure="128" /><Point X="849" Y="392" T="1649871765455" Pressure="128" /><Point X="850" Y="400" T="1649871765463" Pressure="128" /><Point X="850" Y="408" T="1649871765473" Pressure="128" /><Point X="850" Y="415" T="1649871765483" Pressure="128" /><Point X="850" Y="421" T="1649871765493" Pressure="128" /><Point X="850" Y="426" T="1649871765503" Pressure="128" /><Point X="850" Y="430" T="1649871765511" Pressure="128" /><Point X="850" Y="430" T="1649871765521" Pressure="128" /></Stroke></Gesture>